MANIFEST.in
README.md
setup.py
./tensorflow_fer/model/checkpoint
./tensorflow_fer/model/ckpt-50.data-00000-of-00002
./tensorflow_fer/model/ckpt-50.data-00001-of-00002
./tensorflow_fer/model/ckpt-50.index
tensorflow_fer/__init__.py
tensorflow_fer/emotion_recognition.py
tensorflow_fer.egg-info/PKG-INFO
tensorflow_fer.egg-info/SOURCES.txt
tensorflow_fer.egg-info/dependency_links.txt
tensorflow_fer.egg-info/requires.txt
tensorflow_fer.egg-info/top_level.txt
tensorflow_fer/model/checkpoint
tensorflow_fer/model/ckpt-50.data-00000-of-00002
tensorflow_fer/model/ckpt-50.data-00001-of-00002
tensorflow_fer/model/ckpt-50.index